popgui/__init__.py
popgui-0.0.1.dist-info/LICENSE
popgui-0.0.1.dist-info/METADATA
popgui-0.0.1.dist-info/WHEEL
popgui-0.0.1.dist-info/top_level.txt
popgui-0.0.1.dist-info/RECORD
